.travis.yml
AUTHORS
ChangeLog
LICENSE.txt
MANIFEST.in
README.rst
requirements.txt
setup.cfg
setup.py
test-requirements.txt
tox.ini
tests/__init__.py
tests/test_glance_image_filter.py
tests/test_keystone_user_filter.py
wafflehaus/__init__.py
wafflehaus.iweb.egg-info/PKG-INFO
wafflehaus.iweb.egg-info/SOURCES.txt
wafflehaus.iweb.egg-info/dependency_links.txt
wafflehaus.iweb.egg-info/namespace_packages.txt
wafflehaus.iweb.egg-info/not-zip-safe
wafflehaus.iweb.egg-info/pbr.json
wafflehaus.iweb.egg-info/requires.txt
wafflehaus.iweb.egg-info/top_level.txt
wafflehaus/iweb/__init__.py
wafflehaus/iweb/glance/__init__.py
wafflehaus/iweb/glance/image_filter/README.rst
wafflehaus/iweb/glance/image_filter/__init__.py
wafflehaus/iweb/glance/image_filter/visible.py
wafflehaus/iweb/keystone/__init__.py
wafflehaus/iweb/keystone/user_filter/README.rst
wafflehaus/iweb/keystone/user_filter/__init__.py
wafflehaus/iweb/keystone/user_filter/blacklist.py