Metadata-Version: 1.0
Name: wafflehaus.iweb
Version: 0.2.0
Summary: A collection of waffles for iWeb
Home-page: https://github.com/mgagne/wafflehaus.iweb
Author: Mathieu Gagne
Author-email: mgagne@iweb.com
License: UNKNOWN
Platform: UNKNOWN
Classifier: Development Status :: 4 - Beta
Classifier: Environment :: Web Environment
Classifier: Framework :: Paste
Classifier: Intended Audience :: Developers
Classifier: Intended Audience :: System Administrators
Classifier: License :: OSI Approved :: Apache Software License
Classifier: Operating System :: OS Independent
Classifier: Programming Language :: Python :: 2.7
Classifier: Programming Language :: Python :: 2.6
Classifier: Topic :: Internet :: WWW/HTTP :: WSGI :: Middleware
